InterestPrint.py
interestprint-0.7.1.dist-info/METADATA
interestprint-0.7.1.dist-info/WHEEL
interestprint-0.7.1.dist-info/top_level.txt
interestprint-0.7.1.dist-info/RECORD
